tests/__init__.py
tests/iotest/__init__.py
tests/iotest/depth_test.py
tests/iotest/packing_test.py
vathos-2.1.5.dist-info/licenses/LICENSE
vathos_vision/__init__.py
vathos_vision/authentication.py
vathos_vision/configurations.py
vathos_vision/files.py
vathos_vision/grippers.py
vathos_vision/images.py
vathos_vision/products.py
vathos_vision/io/__init__.py
vathos_vision/io/depth.py
vathos_vision/io/packing.py
vathos_vision/services/__init__.py
vathos_vision/services/depalletizing.py
vathos_vision/services/handeye2d.py
vathos-2.1.5.dist-info/METADATA
vathos-2.1.5.dist-info/WHEEL
vathos-2.1.5.dist-info/top_level.txt
vathos-2.1.5.dist-info/RECORD
