Metadata-Version: 2.4
Name: vathos
Version: 2.1.5
Summary: Vathos Vision Python API.
Home-page: https://www.vathos-robotics.com
Author: Jonathan Balzer
Author-email: jonathan.balzer@vathos.net
License-File: LICENSE
Requires-Dist: requests>=2.27.0
Requires-Dist: numpy>=1.22.0
Requires-Dist: imageio>=2.14.0
Dynamic: author
Dynamic: author-email
Dynamic: description
Dynamic: description-content-type
Dynamic: home-page
Dynamic: license-file
Dynamic: requires-dist
Dynamic: summary
